cdktf_cdktf_provider_nomad/__init__.py
cdktf_cdktf_provider_nomad/py.typed
cdktf_cdktf_provider_nomad/_jsii/__init__.py
cdktf_cdktf_provider_nomad/_jsii/provider-nomad@10.0.2.jsii.tgz
cdktf_cdktf_provider_nomad/acl_auth_method/__init__.py
cdktf_cdktf_provider_nomad/acl_binding_rule/__init__.py
cdktf_cdktf_provider_nomad/acl_policy/__init__.py
cdktf_cdktf_provider_nomad/acl_role/__init__.py
cdktf_cdktf_provider_nomad/acl_token/__init__.py
cdktf_cdktf_provider_nomad/csi_volume/__init__.py
cdktf_cdktf_provider_nomad/csi_volume_registration/__init__.py
cdktf_cdktf_provider_nomad/data_nomad_acl_policies/__init__.py
cdktf_cdktf_provider_nomad/data_nomad_acl_policy/__init__.py
cdktf_cdktf_provider_nomad/data_nomad_acl_role/__init__.py
cdktf_cdktf_provider_nomad/data_nomad_acl_roles/__init__.py
cdktf_cdktf_provider_nomad/data_nomad_acl_token/__init__.py
cdktf_cdktf_provider_nomad/data_nomad_acl_tokens/__init__.py
cdktf_cdktf_provider_nomad/data_nomad_allocations/__init__.py
cdktf_cdktf_provider_nomad/data_nomad_datacenters/__init__.py
cdktf_cdktf_provider_nomad/data_nomad_deployments/__init__.py
cdktf_cdktf_provider_nomad/data_nomad_dynamic_host_volume/__init__.py
cdktf_cdktf_provider_nomad/data_nomad_job/__init__.py
cdktf_cdktf_provider_nomad/data_nomad_job_parser/__init__.py
cdktf_cdktf_provider_nomad/data_nomad_jwks/__init__.py
cdktf_cdktf_provider_nomad/data_nomad_namespace/__init__.py
cdktf_cdktf_provider_nomad/data_nomad_namespaces/__init__.py
cdktf_cdktf_provider_nomad/data_nomad_node_pool/__init__.py
cdktf_cdktf_provider_nomad/data_nomad_node_pools/__init__.py
cdktf_cdktf_provider_nomad/data_nomad_plugin/__init__.py
cdktf_cdktf_provider_nomad/data_nomad_plugins/__init__.py
cdktf_cdktf_provider_nomad/data_nomad_regions/__init__.py
cdktf_cdktf_provider_nomad/data_nomad_scaling_policies/__init__.py
cdktf_cdktf_provider_nomad/data_nomad_scaling_policy/__init__.py
cdktf_cdktf_provider_nomad/data_nomad_scheduler_config/__init__.py
cdktf_cdktf_provider_nomad-10.0.2.dist-info/LICENSE
cdktf_cdktf_provider_nomad-10.0.2.dist-info/METADATA
cdktf_cdktf_provider_nomad-10.0.2.dist-info/WHEEL
cdktf_cdktf_provider_nomad-10.0.2.dist-info/top_level.txt
cdktf_cdktf_provider_nomad-10.0.2.dist-info/RECORD
